{
  "task_id": "47d66551",
  "record": {
    "id": "Ελληνική Εταιρεία Νόσου Alzheimer & Συγγενών Διαταραχών",
    "name": "Ελληνική Εταιρεία Νόσου Alzheimer & Συγγενών Διαταραχών",
    "website": "https://www.alzheimer-hellas.gr/",
    "email": "",
    "facebook": "https://www.facebook.com/AlzheimerHellas/",
    "linkedin": "https://www.linkedin.com/company/greek-association-of-alzheimer%E2%80%99s-disease-and-related-disorders-alzheimer-hellas/",
    "instagram": "",
    "source": "ngo"
  },
  "field": "email",
  "status": "pending",
  "result": null,
  "created": "2026-04-29T15:10:50.306820"
}